meetings_reporter/Meeting.py
meetings_reporter/__init__.py
meetings_reporter/meetings_report.py
meetings_reporter-0.2.1.dist-info/METADATA
meetings_reporter-0.2.1.dist-info/WHEEL
meetings_reporter-0.2.1.dist-info/RECORD
