Metadata-Version: 2.1
Name: meetings-reporter
Version: 0.2.1
Summary: 
Home-page: https://github.com/mklkun/meetings-reporter
License: MIT
Keywords: meetings-reporter,meetings-report
Author: mklkun
Author-email: mohamed.khalil.labidi@gmail.com
Requires-Python: >=3.7.1,<4.0.0
Classifier: License :: OSI Approved :: MIT License
Classifier: Programming Language :: Python :: 3
Classifier: Programming Language :: Python :: 3.8
Classifier: Programming Language :: Python :: 3.9
Classifier: Programming Language :: Python :: 3.10
Classifier: Programming Language :: Python :: 3.11
Requires-Dist: pandas (>=1.3.5,<2.0.0)
Project-URL: Repository, https://github.com/mklkun/meetings-reporter
